NumpyShuzuXuexiShouceChuyi/README.md
NumpyShuzuXuexiShouceChuyi/__init__.py
NumpyShuzuXuexiShouceChuyi/__main__.py
NumpyShuzuXuexiShouceChuyi/file.epub
NumpyShuzuXuexiShouceChuyi/index.html
NumpyShuzuXuexiShouceChuyi/css/__init__.py
NumpyShuzuXuexiShouceChuyi/css/annotations.css
NumpyShuzuXuexiShouceChuyi/css/main.css
NumpyShuzuXuexiShouceChuyi/css/normalize.css
NumpyShuzuXuexiShouceChuyi/css/popup.css
NumpyShuzuXuexiShouceChuyi/font/__init__.py
NumpyShuzuXuexiShouceChuyi/font/fontello.eot
NumpyShuzuXuexiShouceChuyi/font/fontello.svg
NumpyShuzuXuexiShouceChuyi/font/fontello.ttf
NumpyShuzuXuexiShouceChuyi/font/fontello.woff
NumpyShuzuXuexiShouceChuyi/img/__init__.py
NumpyShuzuXuexiShouceChuyi/img/annotator-glyph-sprite.png
NumpyShuzuXuexiShouceChuyi/img/annotator-icon-sprite.png
NumpyShuzuXuexiShouceChuyi/img/apple-touch-icon.png
NumpyShuzuXuexiShouceChuyi/img/cancelfullscreen.png
NumpyShuzuXuexiShouceChuyi/img/close.png
NumpyShuzuXuexiShouceChuyi/img/fullscreen.png
NumpyShuzuXuexiShouceChuyi/img/loader.gif
NumpyShuzuXuexiShouceChuyi/img/menu-icon.png
NumpyShuzuXuexiShouceChuyi/img/save.png
NumpyShuzuXuexiShouceChuyi/img/saved.png
NumpyShuzuXuexiShouceChuyi/img/settings-s.png
NumpyShuzuXuexiShouceChuyi/img/settings.png
NumpyShuzuXuexiShouceChuyi/img/star.png
NumpyShuzuXuexiShouceChuyi/js/__init__.py
NumpyShuzuXuexiShouceChuyi/js/epub.js
NumpyShuzuXuexiShouceChuyi/js/epub.min.js
NumpyShuzuXuexiShouceChuyi/js/epub.min.map
NumpyShuzuXuexiShouceChuyi/js/hooks.min.js
NumpyShuzuXuexiShouceChuyi/js/hooks.min.map
NumpyShuzuXuexiShouceChuyi/js/reader.js
NumpyShuzuXuexiShouceChuyi/js/reader.js.map
NumpyShuzuXuexiShouceChuyi/js/reader.min.js
NumpyShuzuXuexiShouceChuyi/js/reader.min.map
NumpyShuzuXuexiShouceChuyi/js/hooks/__init__.py
NumpyShuzuXuexiShouceChuyi/js/hooks/extensions/__init__.py
NumpyShuzuXuexiShouceChuyi/js/hooks/extensions/highlight.js
NumpyShuzuXuexiShouceChuyi/js/libs/__init__.py
NumpyShuzuXuexiShouceChuyi/js/libs/jquery.min.js
numpy_shuzu_xuexi_shouce_chuyi-2024.3.5.0.dist-info/METADATA
numpy_shuzu_xuexi_shouce_chuyi-2024.3.5.0.dist-info/WHEEL
numpy_shuzu_xuexi_shouce_chuyi-2024.3.5.0.dist-info/entry_points.txt
numpy_shuzu_xuexi_shouce_chuyi-2024.3.5.0.dist-info/top_level.txt
numpy_shuzu_xuexi_shouce_chuyi-2024.3.5.0.dist-info/RECORD
